LICENSE.md
README.md
setup.py
orm/__init__.py
orm/exceptions.py
orm/fields.py
orm/models.py
savannah.egg-info/PKG-INFO
savannah.egg-info/SOURCES.txt
savannah.egg-info/dependency_links.txt
savannah.egg-info/requires.txt
savannah.egg-info/top_level.txt